odoo/addons/hr_expense_petty_cash_sequence/README.rst
odoo/addons/hr_expense_petty_cash_sequence/__init__.py
odoo/addons/hr_expense_petty_cash_sequence/__manifest__.py
odoo/addons/hr_expense_petty_cash_sequence/data/hr_expense_data.xml
odoo/addons/hr_expense_petty_cash_sequence/i18n/hr_expense_petty_cash_sequence.pot
odoo/addons/hr_expense_petty_cash_sequence/i18n/it.po
odoo/addons/hr_expense_petty_cash_sequence/models/__init__.py
odoo/addons/hr_expense_petty_cash_sequence/models/hr_expense_sheet.py
odoo/addons/hr_expense_petty_cash_sequence/readme/CONFIGURE.rst
odoo/addons/hr_expense_petty_cash_sequence/readme/CONTRIBUTORS.rst
odoo/addons/hr_expense_petty_cash_sequence/readme/DESCRIPTION.rst
odoo/addons/hr_expense_petty_cash_sequence/static/description/icon.png
odoo/addons/hr_expense_petty_cash_sequence/static/description/index.html
odoo/addons/hr_expense_petty_cash_sequence/tests/__init__.py
odoo/addons/hr_expense_petty_cash_sequence/tests/test_hr_expense_petty_cash_sequence.py
odoo13_addon_hr_expense_petty_cash_sequence-13.0.1.0.1.dev5.dist-info/METADATA
odoo13_addon_hr_expense_petty_cash_sequence-13.0.1.0.1.dev5.dist-info/WHEEL
odoo13_addon_hr_expense_petty_cash_sequence-13.0.1.0.1.dev5.dist-info/top_level.txt
odoo13_addon_hr_expense_petty_cash_sequence-13.0.1.0.1.dev5.dist-info/RECORD
